itypes.py
pavan_itypes-1.2.0.dist-info/METADATA
pavan_itypes-1.2.0.dist-info/WHEEL
pavan_itypes-1.2.0.dist-info/top_level.txt
pavan_itypes-1.2.0.dist-info/RECORD
