Metadata-Version: 2.1
Name: pavan-itypes
Version: 1.2.0
Summary: Simple immutable types for python.
Home-page: https://github.com/PavanTatikonda/itypes
Author: Pavan Tatikonda
Author-email: tvs.pavan@gmail.com
License: BSD
Platform: UNKNOWN
Classifier: Development Status :: 3 - Alpha
Classifier: Environment :: Web Environment
Classifier: Intended Audience :: Developers
Classifier: License :: OSI Approved :: BSD License
Classifier: Operating System :: OS Independent
Classifier: Programming Language :: Python
Classifier: Topic :: Internet :: WWW/HTTP
